maplpy/__init__.py
maplpy/libmapl.so.2.6.0
maplpy/maplpy.cpython-37m-x86_64-linux-gnu.so
maplpy-2.6.0.dist-info/METADATA
maplpy-2.6.0.dist-info/WHEEL
maplpy-2.6.0.dist-info/entry_points.txt
maplpy-2.6.0.dist-info/top_level.txt
maplpy-2.6.0.dist-info/RECORD
