Metadata-Version: 2.1
Name: maplpy
Version: 2.6.0
Summary: maplpy is a Python wrapper around MAPL with Pybind11.
Home-page: https://opt.aliyun.com
Author: MindOpt Team
Author-email: solver.damo@list.alibaba-inc.com
Classifier: Intended Audience :: Developers
Classifier: Intended Audience :: Science/Research
Classifier: Operating System :: MacOS :: MacOS X
Classifier: Operating System :: Microsoft :: Windows
Classifier: Operating System :: POSIX :: Linux
Classifier: Programming Language :: Python :: 3.6
Classifier: Programming Language :: Python :: 3.7
Classifier: Programming Language :: Python :: 3.8
Classifier: Programming Language :: Python :: 3.9
Classifier: Programming Language :: Python :: 3.10
Classifier: Programming Language :: Python :: 3.11
Classifier: Programming Language :: Python :: Implementation :: CPython
Requires-Python: >=3.6
Requires-Dist: numpy
Requires-Dist: scipy
